{
 "access": "You are from the Eye of Dread region.",
 "archetype": [
  "Lastwall Sentry"
 ],
 "archetype_category": [
  "Faction"
 ],
 "breadcrumbs_spa": [],
 "category": "archetype",
 "exclude_from_search": false,
 "id": "archetype-15",
 "level": 2,
 "markdown": "<title level=\"1\" right=\"Archetype 2\" pfs=\"Standard\">[Lastwall Sentry](/Archetypes.aspx?ID=15)</title>\n\n<traits>\r\n<trait label=\"Uncommon\" url=\"/Traits.aspx?ID=159\" />\r\n</traits>\n\n<row gap=\"tiny\">**Source** [World Guide](/Sources.aspx?ID=6) pg. 47 <sup>2.0</sup></row>\n\nWhile the nation of Lastwall is gone, leaving only the horror of the Gravelands behind, you refuse to give up and renounce your oaths. You’ve renewed your vows, swearing to combat the influence of the Whispering Tyrant wherever it might strike across Golarion.\n\n<document level=\"2\" id=\"feat-882\" />\r\n\r\n<document\r\nlevel=\"2\"\r\nid=\"feat-3597\"\n\n/>\r\n\r\n<document\r\nlevel=\"2\"\r\nid=\"feat-3598\"\n\n/>\r\n\r\n<document\r\nlevel=\"2\"\r\nid=\"feat-883\"\n\n/>\r\n\r\n<document\r\nlevel=\"2\"\r\nid=\"feat-3599\"\n\n/>\r\n\r\n<document\r\nlevel=\"2\"\r\nid=\"feat-3600\"\n\n/>\r\n\r\n<document\r\nlevel=\"2\"\r\nid=\"feat-884\"\n\n/>\r\n\r\n<document\r\nlevel=\"2\"\r\nid=\"feat-3601\"\n\n/>\r\n\r\n<document\r\nlevel=\"2\"\r\nid=\"feat-2167\"\n\n/>\r\n\r\n<document\r\nlevel=\"2\"\r\nid=\"feat-885\"\n\n/>\r\n\r\n<document\r\nlevel=\"2\"\r\nid=\"feat-3602\"\n\n/>\r\n\r\n<document\r\nlevel=\"2\"\r\nid=\"feat-3603\"\n\n/>\r\n\r\n<document\r\nlevel=\"2\"\r\nid=\"feat-3604\"\n\n/>\r\n\r\n<document\r\nlevel=\"2\"\r\nid=\"feat-3605\"\n\n/>\r\n\r\n<document\r\nlevel=\"2\"\r\nid=\"feat-3606\"\n\n/>\r\n\r\n<document\r\nlevel=\"2\"\r\nid=\"feat-886\"\n\n/>\r\n\r\n<document\r\nlevel=\"2\"\r\nid=\"feat-3607\"\n\n/>\r\n\r\n<document\r\nlevel=\"2\"\r\nid=\"feat-887\"\n\n/>\r\n\r\n<document\r\nlevel=\"2\"\r\nid=\"feat-3608\"\n\n/>\r\n\r\n<document\r\nlevel=\"2\"\r\nid=\"feat-3609\"\n\n/>\r\n\r\n<document\r\nlevel=\"2\"\r\nid=\"feat-3610\"\n\n/>\r\n\r\n<document\r\nlevel=\"2\"\r\nid=\"feat-3611\"\n\n/>",
 "name": "Lastwall Sentry",
 "pfs": "Standard",
 "prerequisite": "member of the Knights of Lastwall; Shield Block",
 "prerequisite_markdown": "member of the Knights of Lastwall; [Shield Block](/Feats.aspx?ID=839)",
 "rarity": "uncommon",
 "release_date": "2019-08-31",
 "resistance": {},
 "search_markdown": "<traits>\r\n<trait label=\"Uncommon\" url=\"/Traits.aspx?ID=159\" />\r\n</traits>\r\n\r\n<additional-info>\r\n<row gap=\"tiny\">**Source** [World Guide](/Sources.aspx?ID=6) pg. 47 <sup>2.0</sup></row>\r\n\r\n**Prerequisites**\r\nmember of the Knights of Lastwall; [Shield Block](/Feats.aspx?ID=839)\r\n\r\n**Access**\r\nYou are from the Eye of Dread region.\n\n</additional-info>\r\n\r\n---\r\n\r\n<summary>\r\nWhile the nation of Lastwall is gone, leaving only the horror of the Gravelands behind, you refuse to give up and renounce your oaths. You’ve renewed …\r\n</summary>",
 "source": [
  "World Guide"
 ],
 "source_raw": [
  "World Guide pg. 47"
 ],
 "source_category": "Lost Omens",
 "source_markdown": "<row gap=\"tiny\">[World Guide](/Sources.aspx?ID=6) pg. 47 <sup>2.0</sup></row>",
 "speed": {},
 "summary": "While the nation of Lastwall is gone, leaving only the horror of the Gravelands behind, you refuse to give up and renounce your oaths. You’ve renewed …",
 "summary_markdown": "While the nation of Lastwall is gone, leaving only the horror of the Gravelands behind, you refuse to give up and renounce your oaths. You’ve renewed …",
 "text": " Lastwall Sentry Source World Guide pg. 47 2.0 While the nation of Lastwall is gone, leaving only the horror of the Gravelands behind, you refuse to give up and renounce your oaths. You’ve renewed your vows, swearing to combat the influence of the Whispering Tyrant wherever it might strike across Golarion. <document level=\"2\" id=\"feat-3597\" /> <document level=\"2\" id=\"feat-3598\" /> <document level=\"2\" id=\"feat-883\" /> <document level=\"2\" id=\"feat-3599\" /> <document level=\"2\" id=\"feat-3600\" /> <document level=\"2\" id=\"feat-884\" /> <document level=\"2\" id=\"feat-3601\" /> <document level=\"2\" id=\"feat-2167\" /> <document level=\"2\" id=\"feat-885\" /> <document level=\"2\" id=\"feat-3602\" /> <document level=\"2\" id=\"feat-3603\" /> <document level=\"2\" id=\"feat-3604\" /> <document level=\"2\" id=\"feat-3605\" /> <document level=\"2\" id=\"feat-3606\" /> <document level=\"2\" id=\"feat-886\" /> <document level=\"2\" id=\"feat-3607\" /> <document level=\"2\" id=\"feat-887\" /> <document level=\"2\" id=\"feat-3608\" /> <document level=\"2\" id=\"feat-3609\" /> <document level=\"2\" id=\"feat-3610\" /> <document level=\"2\" id=\"feat-3611\" />",
 "trait": [
  "Uncommon"
 ],
 "trait_markdown": "[Uncommon](/Traits.aspx?ID=159)",
 "trait_raw": [
  "Uncommon"
 ],
 "type": "Archetype",
 "url": "/Archetypes.aspx?ID=15",
 "weakness": {}
}