{
 "breadcrumbs_spa": [],
 "category": "trait",
 "exclude_from_search": false,
 "id": "trait-318",
 "markdown": "<title level=\"1\" right=\"Trait\">[Investigator](/Traits.aspx?ID=318)</title>\r\n\r\n<row gap=\"tiny\">**Source** [Advanced Player's Guide](/Sources.aspx?ID=39) pg. 268 <sup>2.0</sup></row>\n\nThis trait indicates abilities from the [investigator](/Classes.aspx?ID=13) class.",
 "name": "Investigator",
 "rarity": "common",
 "release_date": "2020-07-30",
 "resistance": {},
 "search_markdown": "<additional-info>\r\n<row gap=\"tiny\">**Source** [Advanced Player's Guide](/Sources.aspx?ID=39) pg. 268 <sup>2.0</sup></row>\r\n</additional-info>\r\n\r\n---\r\n\r\n<summary>\r\nThis trait indicates abilities from the  investigator  class.\r\n</summary>",
 "source": [
  "Advanced Player's Guide"
 ],
 "source_raw": [
  "Advanced Player's Guide pg. 268"
 ],
 "source_category": "Rulebooks",
 "source_markdown": "<row gap=\"tiny\">[Advanced Player's Guide](/Sources.aspx?ID=39) pg. 268 <sup>2.0</sup></row>",
 "speed": {},
 "summary": "This trait indicates abilities from the  investigator  class.",
 "summary_markdown": "This trait indicates abilities from the  investigator  class.",
 "text": " Investigator Source Advanced Player's Guide pg. 268 2.0 This trait indicates abilities from the investigator class.",
 "trait": [
  "Investigator"
 ],
 "trait_group": [
  "Class"
 ],
 "trait_markdown": "Investigator",
 "trait_raw": [
  "Investigator"
 ],
 "type": "Trait",
 "url": "/Traits.aspx?ID=318",
 "weakness": {}
}