{
 "breadcrumbs_spa": [],
 "category": "trait",
 "exclude_from_search": false,
 "id": "trait-414",
 "markdown": "<title level=\"1\" right=\"Trait\">[Spellshot](/Traits.aspx?ID=414)</title>\r\n\r\n<row gap=\"tiny\">**Source** [Guns &amp; Gears](/Sources.aspx?ID=98) pg. 140</row>\n\n_Note from Nethys: no description was provided for this trait_",
 "name": "Spellshot",
 "rarity": "common",
 "release_date": "2021-10-13",
 "resistance": {},
 "search_markdown": "<additional-info>\r\n<row gap=\"tiny\">**Source** [Guns &amp; Gears](/Sources.aspx?ID=98) pg. 140</row>\r\n</additional-info>\r\n\r\n---\r\n\r\n<summary>\r\n Note from Nethys: no description was provided for this trait \r\n</summary>",
 "source": [
  "Guns & Gears"
 ],
 "source_raw": [
  "Guns & Gears pg. 140"
 ],
 "source_category": "Rulebooks",
 "source_markdown": "<row gap=\"tiny\">[Guns &amp; Gears](/Sources.aspx?ID=98) pg. 140</row>",
 "speed": {},
 "summary": " Note from Nethys: no description was provided for this trait ",
 "summary_markdown": " Note from Nethys: no description was provided for this trait ",
 "text": " Spellshot Source Guns &amp; Gears pg. 140 Note from Nethys: no description was provided for this trait ",
 "trait": [
  "Spellshot"
 ],
 "trait_group": [
  "Class-Specific"
 ],
 "trait_markdown": "Spellshot",
 "trait_raw": [
  "Spellshot"
 ],
 "type": "Trait",
 "url": "/Traits.aspx?ID=414",
 "weakness": {}
}