{
 "ac": 20,
 "alignment": "CG",
 "breadcrumbs_spa": [],
 "category": "creature",
 "charisma": 2,
 "constitution": 0,
 "creature_ability": [
  "Anadi Venom",
  "Change Shape",
  "Spin Silk"
 ],
 "creature_family": "Anadi",
 "creature_family_markdown": "[Anadi](/MonsterFamilies.aspx?ID=107)",
 "dexterity": 2,
 "exclude_from_search": false,
 "fortitude_save": 8,
 "hp": 58,
 "hp_raw": "58",
 "id": "creature-1423",
 "image": [
  "/Images/Monsters/Anadi_AnadiSage.png"
 ],
 "intelligence": 1,
 "language": [
  "Anadi",
  "Mwangi"
 ],
 "language_markdown": "[Anadi](/Languages.aspx?ID=46), [Mwangi](/Languages.aspx?ID=39)",
 "level": 4,
 "markdown": "<title level=\"1\" pfs=\"Standard\">[Anadi Sage](/Monsters.aspx?ID=1423)</title>\r\n\r\n<row gap=\"medium\">\r\n\r\n<column gap=\"medium\" flex=\"1 1 400px\">\r\n\r\nAnadi sages commune with nature and hone their innate magic through practice.\r\n\r\n<column gap=\"tiny\">\r\n**[Recall Knowledge - Humanoid](/Rules.aspx?ID=563)**\r\n([Society](/Skills.aspx?ID=14)): DC 21\r\n\r\n**[Unspecific Lore](/Rules.aspx?ID=563)**: DC 19\r\n\r\n**[Specific Lore](/Rules.aspx?ID=563)**: DC 16\r\n</column>\r\n\r\n</column>\r\n\r\n<column gap=\"medium\">\r\n<image src=\"/images/Monsters/Anadi_AnadiSage.png\" />\r\n</column>\r\n\r\n</row>\r\n\r\n<title level=\"2\" right=\"Creature 4\">[Anadi Sage](/Monsters.aspx?ID=1423)</title>\r\n\r\n<traits>\r\n<trait label=\"Uncommon\" url=\"/Traits.aspx?ID=159\" />\r\n<trait label=\"CG\" url=\"/Rules.aspx?ID=95\" />\r\n<trait label=\"Medium\" />\r\n<trait label=\"Anadi\" url=\"/Traits.aspx?ID=255\" />\r\n<trait label=\"Humanoid\" url=\"/Traits.aspx?ID=91\" />\r\n</traits>\r\n\r\n<column gap=\"tiny\">\r\n\r\n<row gap=\"tiny\">**Source** [The Mwangi Expanse](/Sources.aspx?ID=89) pg. 290 <sup>2.0</sup>, [Pathfinder #145: Hellknight Hill](/Sources.aspx?ID=4) pg. 85</row>\n\n**Perception** +12\r\n\r\n**Languages**\r\n[Anadi](/Languages.aspx?ID=46), [Mwangi](/Languages.aspx?ID=39)\r\n\r\n**Skills**\r\n[Athletics](/Skills.aspx?ID=3) +12, [Crafting](/Skills.aspx?ID=4) +10, [Deception](/Skills.aspx?ID=5) +8, [Diplomacy](/Skills.aspx?ID=6) +10, [Nature](/Skills.aspx?ID=10) +12, [Survival](/Skills.aspx?ID=16) +10\r\n\r\n<row gap=\"medium\">\r\n**Str** +0\r\n\r\n**Dex** +2\r\n\r\n**Con** +0\r\n\r\n**Int** +1\r\n\r\n**Wis** +4\r\n\r\n**Cha** +2\r\n</row>\n\n**Items**\r\n[Hide Armor](/Armor.aspx?ID=7), [Shortsword](/Weapons.aspx?ID=43)\r\n\r\n</column>\r\n\r\n---\r\n\r\n<column gap=\"tiny\">\r\n\r\n<row gap=\"medium\">\r\n**AC** 20 \r\n\r\n**Fort** +8 \r\n\r\n**Ref** +11 \r\n\r\n**Will** +14 \n\n</row>\r\n\r\n**HP** 58\n\n</column>\r\n\r\n---\r\n\r\n<column gap=\"tiny\">\r\n\r\n**Speed** 25 feet, climb 25 feet\r\n\r\n**Melee**\r\n<actions string=\"Single Action\" />\r\nshortsword +12 ([Agile](/Traits.aspx?ID=170), [Finesse](/Traits.aspx?ID=179), [versatile S](/Traits.aspx?ID=200)),\r\n**Damage** 1d6+3 piercing\r\n\r\n**Melee**\r\n<actions string=\"Single Action\" />\r\nfangs +12 ([Finesse](/Traits.aspx?ID=179)),\r\n**Damage** 2d6+3 piercing plus anadi venom\r\n\r\n**Arcane Innate Spells** DC 21\r\n- **Cantrips (2nd)**\r\n[Detect Magic](/Spells.aspx?ID=66), [Ghost Sound](/Spells.aspx?ID=132), [Mage Hand](/Spells.aspx?ID=177), [Message](/Spells.aspx?ID=190)\r\n- **1st**\r\n[Color Spray](/Spells.aspx?ID=44), [Illusory Disguise](/Spells.aspx?ID=159), [Illusory Object](/Spells.aspx?ID=160)\r\n- **2nd**\r\n[Blur](/Spells.aspx?ID=28), [Illusory Creature](/Spells.aspx?ID=158)\r\n\r\n**Anadi Venom**  ([Poison](/Traits.aspx?ID=126)) **Saving Throw** DC 19 Fortitude; **Maximum Duration** 4 rounds; **Stage 1** 1d6 poison damage and [flat-footed](/Conditions.aspx?ID=16) (1 round); **Stage 2** 1d6 poison damage, flat-footed, and [clumsy 1](/Conditions.aspx?ID=3) (1 round)\r\n\r\n**[Change Shape](/MonsterAbilities.aspx?ID=8)** <actions string=\"Single Action\" /> ([Arcane](/Traits.aspx?ID=11), [Concentrate](/Traits.aspx?ID=32), [Polymorph](/Traits.aspx?ID=127), [Transmutation](/Traits.aspx?ID=157)) The anadi changes into their hybrid form, spider form, or human form. The above statistics assume the anadi is in their hybrid form. While in their human form, the anadi hunter can't use their fangs attack and loses their climb Speed. When in spider form, they can't use weapons.\r\n\r\n**Spin Silk**  ([Concentrate](/Traits.aspx?ID=32), [Exploration](/Traits.aspx?ID=66), [Manipulate](/Traits.aspx?ID=104)) By spending several minutes, an anadi can produce silk to craft items made of cloth. A single anadi can produce enough silk in a day to craft a single garment.\r\n\r\n</column>\n\n<document level=\"2\" id=\"creature-family-107\" />",
 "name": "Anadi Sage",
 "npc": false,
 "perception": 12,
 "pfs": "Standard",
 "rarity": "uncommon",
 "reflex_save": 11,
 "release_date": "2021-07-07",
 "resistance": {},
 "search_markdown": "<traits>\r\n<trait label=\"Uncommon\" url=\"/Traits.aspx?ID=159\" />\r\n<trait label=\"Anadi\" url=\"/Traits.aspx?ID=255\" />\r\n<trait label=\"Humanoid\" url=\"/Traits.aspx?ID=91\" />\r\n</traits>\r\n\r\n<additional-info>\r\n<row gap=\"tiny\">**Sources** [The Mwangi Expanse](/Sources.aspx?ID=89) pg. 290 <sup>2.0</sup>, [Pathfinder #145: Hellknight Hill](/Sources.aspx?ID=4) pg. 85</row>\r\n\r\n**Creature Family** [Anadi](/MonsterFamilies.aspx?ID=107)\r\n\r\n<row gap=\"medium\">\r\n**HP** 58\r\n\r\n**AC** 20\r\n\r\n**Fort** +8\r\n\r\n**Ref** +11\r\n\r\n**Will** +14\r\n\r\n**Perception** +12\r\n</row>\r\n</additional-info>\r\n\r\n---\r\n\r\n<summary>\r\nAnadi sages commune with nature and hone their innate magic through practice.\r\n</summary>",
 "size": [
  "Medium"
 ],
 "skill": [
  "Athletics +12",
  "Crafting +10",
  "Deception +8",
  "Diplomacy +10",
  "Nature +12",
  "Survival +10"
 ],
 "skill_markdown": "[Athletics](/Skills.aspx?ID=3) +12, [Crafting](/Skills.aspx?ID=4) +10, [Deception](/Skills.aspx?ID=5) +8, [Diplomacy](/Skills.aspx?ID=6) +10, [Nature](/Skills.aspx?ID=10) +12, [Survival](/Skills.aspx?ID=16) +10",
 "source": [
  "The Mwangi Expanse"
 ],
 "source_raw": [
  "The Mwangi Expanse pg. 290"
 ],
 "source_category": "Lost Omens",
 "source_markdown": "<row gap=\"tiny\">[The Mwangi Expanse](/Sources.aspx?ID=89) pg. 290 <sup>2.0</sup>, [Pathfinder #145: Hellknight Hill](/Sources.aspx?ID=4) pg. 85</row>",
 "speed": {
  "climb": 25,
  "land": 25,
  "max": 25
 },
 "speed_markdown": "25 feet, climb 25 feet",
 "speed_raw": "25 feet, climb 25 feet",
 "spell": [
  "Blur",
  "Illusory Creature",
  "Color Spray",
  "Illusory Disguise",
  "Illusory Object",
  "Detect Magic",
  "Ghost Sound",
  "Mage Hand",
  "Message"
 ],
 "spell_markdown": "[Blur](/Spells.aspx?ID=28), [Color Spray](/Spells.aspx?ID=44), [Detect Magic](/Spells.aspx?ID=66), [Ghost Sound](/Spells.aspx?ID=132), [Illusory Creature](/Spells.aspx?ID=158), [Illusory Disguise](/Spells.aspx?ID=159), [Illusory Object](/Spells.aspx?ID=160), [Mage Hand](/Spells.aspx?ID=177), [Message](/Spells.aspx?ID=190)",
 "strength": 0,
 "strongest_save": [
  "will"
 ],
 "summary": "Anadi sages commune with nature and hone their innate magic through practice.",
 "summary_markdown": "Anadi sages commune with nature and hone their innate magic through practice.",
 "text": " Anadi Sage Anadi sages commune with nature and hone their innate magic through practice. Recall Knowledge - Humanoid (Society): DC 21 Unspecific Lore : DC 19 Specific Lore : DC 16 Anadi Sage Source The Mwangi Expanse pg. 290 2.0 , Pathfinder #145: Hellknight Hill pg. 85 Perception +12 Languages Anadi, Mwangi Skills Athletics +12, Crafting +10, Deception +8, Diplomacy +10, Nature +12, Survival +10 Str +0 Dex +2 Con +0 Int +1 Wis +4 Cha +2 Items Hide Armor, Shortsword --- AC 20 Fort +8 Ref +11 Will +14 HP 58 --- Speed 25 feet, climb 25 feet Melee Single Action shortsword +12 (Agile, Finesse, versatile S), Damage 1d6+3 piercing Melee Single Action fangs +12 (Finesse), Damage 2d6+3 piercing plus anadi venom Arcane Innate Spells DC 21 - Cantrips (2nd) Detect Magic, Ghost Sound, Mage Hand, Message - 1st Color Spray, Illusory Disguise, Illusory Object - 2nd Blur, Illusory Creature Anadi Venom (Poison) Saving Throw DC 19 Fortitude; Maximum Duration 4 rounds; Stage 1 1d6 poison damage and flat-footed (1 round); Stage 2 1d6 poison damage, flat-footed, and clumsy 1 (1 round) Change Shape Single Action (Arcane, Concentrate, Polymorph, Transmutation) The anadi changes into their hybrid form, spider form, or human form. The above statistics assume the anadi is in their hybrid form. While in their human form, the anadi hunter can't use their fangs attack and loses their climb Speed. When in spider form, they can't use weapons. Spin Silk (Concentrate, Exploration, Manipulate) By spending several minutes, an anadi can produce silk to craft items made of cloth. A single anadi can produce enough silk in a day to craft a single garment. ",
 "trait": [
  "Anadi",
  "Humanoid",
  "Uncommon",
  "CG",
  "Medium"
 ],
 "trait_markdown": "[Anadi](/Traits.aspx?ID=255), [Humanoid](/Traits.aspx?ID=91), [Uncommon](/Traits.aspx?ID=159)",
 "trait_raw": [
  "Anadi",
  "Humanoid",
  "Uncommon"
 ],
 "type": "Creature",
 "url": "/Monsters.aspx?ID=1423",
 "weakest_save": [
  "fort",
  "fortitude"
 ],
 "weakness": {},
 "will_save": 14,
 "wisdom": 4
}