{
 "ac": 22,
 "alignment": "NG",
 "breadcrumbs_spa": [],
 "category": "creature",
 "charisma": 0,
 "constitution": 3,
 "creature_ability": [
  "Bravery",
  "Attack of Opportunity",
  "Offensive Line"
 ],
 "creature_family_markdown": "",
 "dexterity": 1,
 "exclude_from_search": false,
 "fortitude_save": 15,
 "hp": 80,
 "hp_raw": "80",
 "id": "creature-2089",
 "intelligence": 0,
 "language": [
  "Drooni"
 ],
 "language_markdown": "[Drooni](/Languages.aspx?ID=100)",
 "level": 5,
 "markdown": "<title level=\"1\" pfs=\"\">[Nwanyian Defender](/NPCs.aspx?ID=2089)</title>\r\n\r\n<row gap=\"medium\">\r\n\r\n<column gap=\"medium\" flex=\"1 1 400px\">\n\n<column gap=\"tiny\">\r\n**[Recall Knowledge - Humanoid](/Rules.aspx?ID=563)**\r\n([Society](/Skills.aspx?ID=14)): DC 22\r\n\r\n**[Unspecific Lore](/Rules.aspx?ID=563)**: DC 20\r\n\r\n**[Specific Lore](/Rules.aspx?ID=563)**: DC 17\r\n</column>\r\n\r\n</column>\r\n\r\n<column gap=\"medium\">\r\n\r\n</column>\r\n\r\n</row>\r\n\r\n<title level=\"2\" right=\"Creature 5\">[Nwanyian Defender](/NPCs.aspx?ID=2089)</title>\r\n\r\n<traits>\r\n<trait label=\"Uncommon\" url=\"/Traits.aspx?ID=159\" />\r\n<trait label=\"NG\" url=\"/Rules.aspx?ID=95\" />\r\n<trait label=\"Medium\" />\r\n<trait label=\"Human\" url=\"/Traits.aspx?ID=90\" />\r\n<trait label=\"Humanoid\" url=\"/Traits.aspx?ID=91\" />\r\n</traits>\r\n\r\n<column gap=\"tiny\">\r\n\r\n<row gap=\"tiny\">**Source** [Pathfinder #183: Field of Maidens](/Sources.aspx?ID=145) pg. 38</row>\n\n**Perception** +12\r\n\r\n**Languages**\r\n[Drooni](/Languages.aspx?ID=100)\r\n\r\n**Skills**\r\n[Athletics](/Skills.aspx?ID=3) +13, [Intimidation](/Skills.aspx?ID=7) +11, [Survival](/Skills.aspx?ID=16) +12\r\n\r\n<row gap=\"medium\">\r\n**Str** +4\r\n\r\n**Dex** +1\r\n\r\n**Con** +3\r\n\r\n**Int** +0\r\n\r\n**Wis** +3\r\n\r\n**Cha** +0\r\n</row>\r\n\r\n**Bravery** Whenever the defender rolls a success at a Will save against a [fear](/Traits.aspx?ID=68) effect, they get a critical success instead. In addition, any time they gain the [frightened](/Conditions.aspx?ID=19) condition, they reduce its value by 1.\r\n\r\n**Items**\r\n[Breastplate](/Armor.aspx?ID=10), [Composite Shortbow](/Weapons.aspx?ID=75) (20 arrows), _+1 [guisarme](/Weapons.aspx?ID=25)_\r\n\r\n</column>\r\n\r\n---\r\n\r\n<column gap=\"tiny\">\r\n\r\n<row gap=\"medium\">\r\n**AC** 22 \r\n\r\n**Fort** +15 \r\n\r\n**Ref** +9 \r\n\r\n**Will** +12 \n\n</row>\r\n\r\n**HP** 80\n\n**[Attack of Opportunity](/MonsterAbilities.aspx?ID=3)** <actions string=\"Reaction\" /> \r\n\r\n</column>\r\n\r\n---\r\n\r\n<column gap=\"tiny\">\r\n\r\n**Speed** 25 feet\r\n\r\n**Melee**\r\n<actions string=\"Single Action\" />\r\n_guisarme_ +15 ([Magical](/Traits.aspx?ID=103), [Reach](/Traits.aspx?ID=192), [Trip](/Traits.aspx?ID=196)),\r\n**Damage** 1d10+8 slashing\r\n\r\n**Ranged**\r\n<actions string=\"Single Action\" />\r\ncomposite shortbow +11 ([deadly d10](/Traits.aspx?ID=174), [Propulsive](/Traits.aspx?ID=191), [range increment 60 feet](/Traits.aspx?ID=248)),\r\n**Damage** 1d6+4 piercing\n\n**Offensive Line**   The defender's Strikes deal an extra 1d6 damage when adjacent to an ally.\r\n\r\n</column>",
 "name": "Nwanyian Defender",
 "npc": true,
 "perception": 12,
 "rarity": "uncommon",
 "reflex_save": 9,
 "release_date": "2022-09-21",
 "resistance": {},
 "search_markdown": "<traits>\r\n<trait label=\"Uncommon\" url=\"/Traits.aspx?ID=159\" />\r\n<trait label=\"Human\" url=\"/Traits.aspx?ID=90\" />\r\n<trait label=\"Humanoid\" url=\"/Traits.aspx?ID=91\" />\r\n</traits>\r\n\r\n<additional-info>\r\n<row gap=\"tiny\">**Source** [Pathfinder #183: Field of Maidens](/Sources.aspx?ID=145) pg. 38</row>\n\n<row gap=\"medium\">\r\n**HP** 80\r\n\r\n**AC** 22\r\n\r\n**Fort** +15\r\n\r\n**Ref** +9\r\n\r\n**Will** +12\r\n\r\n**Perception** +12\r\n</row>\r\n</additional-info>\r\n\r\n---\r\n\r\n<summary>\r\n\r\n</summary>",
 "size": [
  "Medium"
 ],
 "skill": [
  "Athletics +13",
  "Intimidation +11",
  "Survival +12"
 ],
 "skill_markdown": "[Athletics](/Skills.aspx?ID=3) +13, [Intimidation](/Skills.aspx?ID=7) +11, [Survival](/Skills.aspx?ID=16) +12",
 "source": [
  "Pathfinder #183: Field of Maidens"
 ],
 "source_raw": [
  "Pathfinder #183: Field of Maidens pg. 38"
 ],
 "source_category": "Adventure Paths",
 "source_group": "Blood Lords",
 "source_markdown": "<row gap=\"tiny\">[Pathfinder #183: Field of Maidens](/Sources.aspx?ID=145) pg. 38</row>",
 "speed": {
  "land": 25,
  "max": 25
 },
 "speed_markdown": "25 feet",
 "speed_raw": "25 feet",
 "spell_markdown": "",
 "spoilers": "Blood Lords",
 "strength": 4,
 "strongest_save": [
  "fort",
  "fortitude"
 ],
 "text": " Nwanyian Defender Recall Knowledge - Humanoid (Society): DC 22 Unspecific Lore : DC 20 Specific Lore : DC 17 Nwanyian Defender Source Pathfinder #183: Field of Maidens pg. 38 Perception +12 Languages Drooni Skills Athletics +13, Intimidation +11, Survival +12 Str +4 Dex +1 Con +3 Int +0 Wis +3 Cha +0 Bravery Whenever the defender rolls a success at a Will save against a fear effect, they get a critical success instead. In addition, any time they gain the frightened condition, they reduce its value by 1. Items Breastplate, Composite Shortbow (20 arrows), +1 guisarme --- AC 22 Fort +15 Ref +9 Will +12 HP 80 Attack of Opportunity Reaction --- Speed 25 feet Melee Single Action guisarme +15 (Magical, Reach, Trip), Damage 1d10+8 slashing Ranged Single Action composite shortbow +11 (deadly d10, Propulsive, range increment 60 feet), Damage 1d6+4 piercing Offensive Line The defender's Strikes deal an extra 1d6 damage when adjacent to an ally. ",
 "trait": [
  "Human",
  "Humanoid",
  "Uncommon",
  "NG",
  "Medium"
 ],
 "trait_markdown": "[Human](/Traits.aspx?ID=90), [Humanoid](/Traits.aspx?ID=91), [Uncommon](/Traits.aspx?ID=159)",
 "trait_raw": [
  "Human",
  "Humanoid",
  "Uncommon"
 ],
 "type": "Creature",
 "url": "/NPCs.aspx?ID=2089",
 "weakest_save": [
  "ref",
  "reflex"
 ],
 "weakness": {},
 "will_save": 12,
 "wisdom": 3
}