{
 "base_item_markdown": "",
 "breadcrumbs_spa": [],
 "bulk": 1,
 "bulk_raw": "1",
 "category": "equipment",
 "exclude_from_search": false,
 "id": "equipment-268",
 "item_category": "Held Items",
 "level": 6,
 "markdown": "<title\r\n    level=\"1\"\r\n    right=\"Item 6\"\r\n    pfs=\"Standard\"\r\n>\r\n[Traveler's Any-Tool](/Equipment.aspx?ID=268)\r\n</title>\n\n<traits>\r\n<trait label=\"Magical\" url=\"/Traits.aspx?ID=103\" />\r\n<trait label=\"Transmutation\" url=\"/Traits.aspx?ID=157\" />\r\n</traits>\n\n<column gap=\"tiny\">\r\n\r\n<row gap=\"tiny\">**Source** [Core Rulebook](/Sources.aspx?ID=1) pg. 576 <sup>4.0</sup></row>\n\n**Price** 200 gp\r\n\r\n<row gap=\"medium\">\n\n**Usage** held in 2 hands\r\n\r\n**Bulk** 1\r\n</row>\n\n<row gap=\"medium\">\n\n \r\n\r\n \r\n\r\n \r\n</row>\n\n</column>\r\n\r\n---\n\nBefore it’s activated, this item appears to be an ash rod capped with steel on either end.\n\n<document level=\"2\" id=\"action-176\" />\n\n<column gap=\"tiny\">\n\n</column>",
 "name": "Traveler's Any-Tool",
 "pfs": "Standard",
 "price": 20000,
 "price_raw": "200 gp",
 "rarity": "common",
 "release_date": "2019-08-01",
 "resistance": {},
 "school": "transmutation",
 "search_markdown": "<traits>\r\n<trait label=\"Magical\" url=\"/Traits.aspx?ID=103\" />\r\n<trait label=\"Transmutation\" url=\"/Traits.aspx?ID=157\" />\r\n</traits>\r\n\r\n<additional-info>\r\n<row gap=\"tiny\">**Source** [Core Rulebook](/Sources.aspx?ID=1) pg. 576 <sup>4.0</sup></row>\r\n\r\n**Price** 200 gp\r\n\r\n<row gap=\"medium\">\r\n \r\n\r\n**Usage** held in 2 hands\r\n\r\n**Bulk** 1\r\n</row>\r\n\r\n<row gap=\"medium\">\n\n \r\n\r\n \r\n\r\n \r\n</row>\r\n</additional-info>\r\n\r\n---\r\n\r\n<summary>\r\nBefore it’s activated, this item appears to be an ash rod capped with steel on either end. \r\n</summary>",
 "source": [
  "Core Rulebook"
 ],
 "source_raw": [
  "Core Rulebook pg. 576"
 ],
 "source_category": "Rulebooks",
 "source_markdown": "<row gap=\"tiny\">[Core Rulebook](/Sources.aspx?ID=1) pg. 576 <sup>4.0</sup></row>",
 "speed": {},
 "spell_markdown": "",
 "stage_markdown": "",
 "summary": "Before it’s activated, this item appears to be an ash rod capped with steel on either end. ",
 "summary_markdown": "Before it’s activated, this item appears to be an ash rod capped with steel on either end. ",
 "text": "<title level=\"1\" right=\"Item 6\" pfs=\"Standard\" > Traveler's Any-Tool Source Core Rulebook pg. 576 4.0 Price 200 gp Usage held in 2 hands Bulk 1 --- Before it’s activated, this item appears to be an ash rod capped with steel on either end.\n",
 "trait": [
  "Magical",
  "Transmutation"
 ],
 "trait_markdown": "[Magical](/Traits.aspx?ID=103), [Transmutation](/Traits.aspx?ID=157)",
 "trait_raw": [
  "Magical",
  "Transmutation"
 ],
 "type": "Item",
 "url": "/Equipment.aspx?ID=268",
 "usage": "held in 2 hands",
 "usage_markdown": "held in 2 hands",
 "weakness": {}
}