{
 "base_item_markdown": "",
 "breadcrumbs_spa": [],
 "bulk": 1,
 "bulk_raw": "1",
 "category": "equipment",
 "exclude_from_search": false,
 "id": "equipment-364-419",
 "item_category": "Staves",
 "level": 6,
 "markdown": "<title\r\n    level=\"1\"\r\n    right=\"Item 6+\"\r\n    pfs=\"\"\r\n>\r\n[Verdant Staff](/Equipment.aspx?ID=364)\r\n</title>\n\n<traits>\r\n<trait label=\"Divination\" url=\"/Traits.aspx?ID=47\" />\r\n<trait label=\"Magical\" url=\"/Traits.aspx?ID=103\" />\r\n<trait label=\"Staff\" url=\"/Traits.aspx?ID=151\" />\r\n</traits>\n\n<column gap=\"tiny\">\r\n\r\n<row gap=\"tiny\">**Source** [Core Rulebook](/Sources.aspx?ID=1) pg. 595 <sup>4.0</sup></row>\n\n<row gap=\"medium\">\n\n**Usage** held in 1 hand\n\n</row>\n\n<row gap=\"medium\">\n\n \r\n\r\n \r\n\r\n \r\n</row>\n\n</column>\r\n\r\n---\n\nThis oak branch grows leaves in spring that change color in autumn and shed in winter. While wielding it, you gain a +2 circumstance bonus to checks to identify plants and fungi.\n\n<document level=\"2\" id=\"action-197\" />\n\n**Craft Requirements** Supply one casting of all listed levels of all listed spells.\n\n<column gap=\"tiny\">\n\n</column>\r\n\r\n<title\r\nlevel=\"2\"\r\nright=\"Item 6\"\r\npfs=\"Standard\"\r\n>\r\nVerdant Staff\r\n</title>\n\n<traits>\r\n\r\n</traits>\r\n\r\n<column gap=\"tiny\">\r\n\r\n<row gap=\"tiny\">**Source** [Core Rulebook](/Sources.aspx?ID=1) pg. 595 <sup>4.0</sup></row>\n\n**Price** 225 gp\r\n\r\n<row gap=\"medium\">\n\n**Bulk** 1\r\n\r\n</row>\n\n</column>\r\n\r\n---\n\n<ul><li>**Cantrip** [_tanglefoot_](/Spells.aspx?ID=330) </li><li>**1st** [_shillelagh_](/Spells.aspx?ID=282) (can target the _verdant staff_)</li><li>**2nd** [_barkskin_](/Spells.aspx?ID=20), [_entangle_](/Spells.aspx?ID=103), [_shape wood_](/Spells.aspx?ID=277), [_tree shape_](/Spells.aspx?ID=342)</li></ul>\r\n\r\n<title\r\nlevel=\"2\"\r\nright=\"Item 12\"\r\npfs=\"Standard\"\r\n>\r\nVerdant Staff (Greater)\r\n</title>\n\n<traits>\r\n\r\n</traits>\r\n\r\n<column gap=\"tiny\">\r\n\r\n<row gap=\"tiny\">**Source** [Core Rulebook](/Sources.aspx?ID=1) pg. 595 <sup>4.0</sup></row>\n\n**Price** 1,750 gp\r\n\r\n<row gap=\"medium\">\n\n**Bulk** 1\r\n\r\n</row>\n\n</column>\r\n\r\n---\n\n<ul><li>**3rd** [_wall of thorns_](/Spells.aspx?ID=366) </li><li>**4th** _barkskin_, [_speak with plants_](/Spells.aspx?ID=294) </li><li>**5th** [_plant form_](/Spells.aspx?ID=223), _wall of thorns_</li></ul>",
 "name": "Verdant Staff",
 "pfs": "Standard",
 "price": 22500,
 "price_raw": "225 gp",
 "rarity": "common",
 "release_date": "2019-08-01",
 "resistance": {},
 "school": "divination",
 "search_markdown": "<traits>\r\n<trait label=\"Divination\" url=\"/Traits.aspx?ID=47\" />\r\n<trait label=\"Magical\" url=\"/Traits.aspx?ID=103\" />\r\n<trait label=\"Staff\" url=\"/Traits.aspx?ID=151\" />\r\n</traits>\r\n\r\n<additional-info>\r\n<row gap=\"tiny\">**Source** [Core Rulebook](/Sources.aspx?ID=1) pg. 595 <sup>4.0</sup></row>\r\n\r\n**Price** 225 gp\r\n\r\n<row gap=\"medium\">\r\n \r\n\r\n**Usage** held in 1 hand\r\n\r\n**Bulk** 1\r\n</row>\r\n\r\n<row gap=\"medium\">\n\n \r\n\r\n \r\n</row>\r\n</additional-info>\r\n\r\n---\r\n\r\n<summary>\r\n   Cantrip    tanglefoot      1st    shillelagh   (can target the  verdant staff )   2nd    barkskin  ,   entangle  ,   shape wood  ,   tree shape    \r\n</summary>",
 "source": [
  "Core Rulebook"
 ],
 "source_raw": [
  "Core Rulebook pg. 595"
 ],
 "source_category": "Rulebooks",
 "source_markdown": "<row gap=\"tiny\">[Core Rulebook](/Sources.aspx?ID=1) pg. 595 <sup>4.0</sup></row>",
 "speed": {},
 "spell_markdown": "",
 "summary": "   Cantrip    tanglefoot      1st    shillelagh   (can target the  verdant staff )   2nd    barkskin  ,   entangle  ,   shape wood  ,   tree shape    ",
 "summary_markdown": "   Cantrip    tanglefoot      1st    shillelagh   (can target the  verdant staff )   2nd    barkskin  ,   entangle  ,   shape wood  ,   tree shape    ",
 "text": "<title level=\"1\" right=\"Item 6+\" pfs=\"\" > Verdant Staff Source Core Rulebook pg. 595 4.0 Usage held in 1 hand --- This oak branch grows leaves in spring that change color in autumn and shed in winter. While wielding it, you gain a +2 circumstance bonus to checks to identify plants and fungi. Craft Requirements Supply one casting of all listed levels of all listed spells. <title level=\"2\" right=\"Item 6\" pfs=\"Standard\" > Verdant Staff Source Core Rulebook pg. 595 4.0 Price 225 gp Bulk 1 --- Cantrip tanglefoot 1st shillelagh (can target the verdant staff ) 2nd barkskin , entangle , shape wood , tree shape <title level=\"2\" right=\"Item 12\" pfs=\"Standard\" > Verdant Staff (Greater) Source Core Rulebook pg. 595 4.0 Price 1,750 gp Bulk 1 --- 3rd wall of thorns 4th barkskin , speak with plants 5th plant form , wall of thorns ",
 "trait": [
  "Divination",
  "Magical",
  "Staff"
 ],
 "trait_markdown": "[Divination](/Traits.aspx?ID=47), [Magical](/Traits.aspx?ID=103), [Staff](/Traits.aspx?ID=151)",
 "trait_raw": [
  "Divination",
  "Magical",
  "Staff"
 ],
 "type": "Item",
 "url": "/Equipment.aspx?ID=364",
 "usage": "held in 1 hand",
 "usage_markdown": "held in 1 hand",
 "weakness": {}
}